<?xml version="1.0" encoding="UTF-8" standalone="yes"?>
<worksheet xmlns="http://schemas.openxmlformats.org/spreadsheetml/2006/main" xmlns:r="http://schemas.openxmlformats.org/officeDocument/2006/relationships" xmlns:xdr="http://schemas.openxmlformats.org/drawingml/2006/spreadsheetDrawing" xmlns:x14="http://schemas.microsoft.com/office/spreadsheetml/2009/9/main" xmlns:mc="http://schemas.openxmlformats.org/markup-compatibility/2006" xmlns:etc="http://www.wps.cn/officeDocument/2017/etCustomData"><sheetPr/><dimension ref="A1:N86"/><sheetViews><sheetView workbookViewId="0"><selection activeCell="A1" sqref="A1"/></sheetView></sheetViews><sheetFormatPr defaultColWidth="9" defaultRowHeight="14.5"/><cols><col min="1" max="1" width="7.54545454545455" customWidth="1"/><col min="2" max="2" width="23.2727272727273" customWidth="1"/><col min="3" max="3" width="31.0909090909091" customWidth="1"/><col min="4" max="4" width="27.8181818181818" customWidth="1"/><col min="5" max="5" width="23.0909090909091" customWidth="1"/><col min="6" max="6" width="20.8181818181818" customWidth="1"/><col min="7" max="7" width="18.5454545454545" customWidth="1"/><col min="8" max="8" width="25" customWidth="1"/><col min="9" max="9" width="117.727272727273" customWidth="1"/><col min="10" max="10" width="15.0909090909091" customWidth="1"/><col min="11" max="11" width="163" customWidth="1"/><col min="12" max="12" width="78.3636363636364" customWidth="1"/><col min="13" max="13" width="21.2727272727273" customWidth="1"/><col min="14" max="14" width="10.5454545454545" customWidth="1"/></cols><sheetData><row r="1" spans="1:14"><c r="A1" t="s"><v>0</v></c><c r="B1" t="s"><v>1</v></c><c r="C1" t="s"><v>2</v></c><c r="D1" t="s"><v>3</v></c><c r="E1" t="s"><v>21591</v></c><c r="F1" t="s"><v>21592</v></c><c r="G1" t="s"><v>11</v></c><c r="H1" t="s"><v>21593</v></c><c r="I1" t="s"><v>21594</v></c><c r="J1" t="s"><v>12</v></c><c r="K1" t="s"><v>13</v></c><c r="L1" t="s"><v>14</v></c><c r="M1" t="s"><v>15</v></c><c r="N1" t="s"><v>16</v></c></row><row r="2" spans="1:14"><c r="A2" t="s"><v>17</v></c><c r="B2" t="s"><v>18</v></c><c r="C2" t="s"><v>715</v></c><c r="D2" t="s"><v>717</v></c><c r="E2" t="s"><v>21595</v></c><c r="F2" t="s"><v>1157</v></c><c r="G2" t="s"><v>21596</v></c><c r="H2" t="s"><v>21597</v></c><c r="I2" t="s"><v>21598</v></c><c r="K2" t="s"><v>4585</v></c><c r="L2" t="s"><v>177</v></c><c r="M2" t="s"><v>1610</v></c><c r="N2"><v>0</v></c></row><row r="3" spans="1:14"><c r="A3" t="s"><v>30</v></c><c r="B3" t="s"><v>18</v></c><c r="C3" t="s"><v>1551</v></c><c r="D3" t="s"><v>1554</v></c><c r="E3" t="s"><v>21599</v></c><c r="F3" t="s"><v>1555</v></c><c r="G3" t="s"><v>21600</v></c><c r="H3" t="s"><v>21601</v></c><c r="I3" t="s"><v>21602</v></c><c r="L3" t="s"><v>921</v></c><c r="M3" t="s"><v>1761</v></c><c r="N3"><v>0</v></c></row><row r="4" spans="1:14"><c r="A4" t="s"><v>39</v></c><c r="B4" t="s"><v>18</v></c><c r="C4" t="s"><v>1808</v></c><c r="D4" t="s"><v>1811</v></c><c r="E4" t="s"><v>21603</v></c><c r="F4" t="s"><v>21604</v></c><c r="G4" t="s"><v>21605</v></c><c r="H4" t="s"><v>21606</v></c><c r="I4" t="s"><v>21607</v></c><c r="K4" t="s"><v>21608</v></c><c r="L4" t="s"><v>195</v></c><c r="M4" t="s"><v>1873</v></c><c r="N4"><v>0</v></c></row><row r="5" spans="1:14"><c r="A5" t="s"><v>47</v></c><c r="B5" t="s"><v>18</v></c><c r="C5" t="s"><v>1868</v></c><c r="D5" t="s"><v>1871</v></c><c r="E5" t="s"><v>21609</v></c><c r="F5" t="s"><v>83</v></c><c r="G5" t="s"><v>1872</v></c><c r="H5" t="s"><v>21610</v></c><c r="I5" t="s"><v>21611</v></c><c r="K5" t="s"><v>21612</v></c><c r="L5" t="s"><v>1867</v></c><c r="M5" t="s"><v>21613</v></c><c r="N5"><v>0</v></c></row><row r="6" spans="1:14"><c r="A6" t="s"><v>54</v></c><c r="B6" t="s"><v>18</v></c><c r="C6" t="s"><v>2170</v></c><c r="D6" t="s"><v>2173</v></c><c r="E6" t="s"><v>21614</v></c><c r="F6" t="s"><v>45</v></c><c r="G6" t="s"><v>45</v></c><c r="H6" t="s"><v>21615</v></c><c r="I6" t="s"><v>21616</v></c><c r="K6" t="s"><v>21617</v></c><c r="L6" t="s"><v>48</v></c><c r="M6" t="s"><v>2201</v></c><c r="N6"><v>0</v></c></row><row r="7" spans="1:14"><c r="A7" t="s"><v>62</v></c><c r="B7" t="s"><v>18</v></c><c r="C7" t="s"><v>2170</v></c><c r="D7" t="s"><v>2176</v></c><c r="E7" t="s"><v>21614</v></c><c r="F7" t="s"><v>2180</v></c><c r="G7" t="s"><v>67</v></c><c r="H7" t="s"><v>21615</v></c><c r="I7" t="s"><v>21616</v></c><c r="K7" t="s"><v>21617</v></c><c r="L7" t="s"><v>48</v></c><c r="M7" t="s"><v>2201</v></c><c r="N7"><v>0</v></c></row><row r="8" spans="1:14"><c r="A8" t="s"><v>70</v></c><c r="B8" t="s"><v>18</v></c><c r="C8" t="s"><v>2170</v></c><c r="D8" t="s"><v>2179</v></c><c r="E8" t="s"><v>21614</v></c><c r="F8" t="s"><v>2351</v></c><c r="G8" t="s"><v>2351</v></c><c r="H8" t="s"><v>21615</v></c><c r="I8" t="s"><v>21616</v></c><c r="K8" t="s"><v>21617</v></c><c r="L8" t="s"><v>48</v></c><c r="M8" t="s"><v>2201</v></c><c r="N8"><v>0</v></c></row><row r="9" spans="1:14"><c r="A9" t="s"><v>77</v></c><c r="B9" t="s"><v>18</v></c><c r="C9" t="s"><v>2307</v></c><c r="D9" t="s"><v>2310</v></c><c r="E9" t="s"><v>21618</v></c><c r="F9" t="s"><v>67</v></c><c r="G9" t="s"><v>21619</v></c><c r="H9" t="s"><v>21620</v></c><c r="I9" t="s"><v>21621</v></c><c r="K9" t="s"><v>21622</v></c><c r="L9" t="s"><v>163</v></c><c r="M9" t="s"><v>20786</v></c><c r="N9"><v>0</v></c></row><row r="10" spans="1:14"><c r="A10" t="s"><v>85</v></c><c r="B10" t="s"><v>18</v></c><c r="C10" t="s"><v>2147</v></c><c r="D10" t="s"><v>2157</v></c><c r="E10" t="s"><v>21623</v></c><c r="F10" t="s"><v>27</v></c><c r="G10" t="s"><v>27</v></c><c r="H10" t="s"><v>21624</v></c><c r="I10" t="s"><v>21625</v></c><c r="K10" t="s"><v>21626</v></c><c r="L10" t="s"><v>48</v></c><c r="M10" t="s"><v>2359</v></c><c r="N10"><v>0</v></c></row><row r="11" spans="1:14"><c r="A11" t="s"><v>91</v></c><c r="B11" t="s"><v>18</v></c><c r="C11" t="s"><v>1843</v></c><c r="D11" t="s"><v>1846</v></c><c r="E11" t="s"><v>21627</v></c><c r="F11" t="s"><v>83</v></c><c r="G11" t="s"><v>1848</v></c><c r="H11" t="s"><v>21628</v></c><c r="I11" t="s"><v>21629</v></c><c r="K11" t="s"><v>21630</v></c><c r="L11" t="s"><v>4663</v></c><c r="M11" t="s"><v>21631</v></c><c r="N11"><v>0</v></c></row><row r="12" spans="1:14"><c r="A12" t="s"><v>98</v></c><c r="B12" t="s"><v>18</v></c><c r="C12" t="s"><v>2368</v></c><c r="D12" t="s"><v>2371</v></c><c r="E12" t="s"><v>21632</v></c><c r="F12" t="s"><v>83</v></c><c r="G12" t="s"><v>200</v></c><c r="H12" t="s"><v>21633</v></c><c r="I12" t="s"><v>21634</v></c><c r="K12" t="s"><v>4585</v></c><c r="L12" t="s"><v>177</v></c><c r="M12" t="s"><v>21635</v></c><c r="N12"><v>0</v></c></row><row r="13" spans="1:14"><c r="A13" t="s"><v>102</v></c><c r="B13" t="s"><v>18</v></c><c r="C13" t="s"><v>3082</v></c><c r="D13" t="s"><v>3085</v></c><c r="E13" t="s"><v>21636</v></c><c r="F13" t="s"><v>83</v></c><c r="G13" t="s"><v>3182</v></c><c r="H13" t="s"><v>21637</v></c><c r="I13" t="s"><v>21638</v></c><c r="K13" t="s"><v>3143</v></c><c r="L13" t="s"><v>3144</v></c><c r="M13" t="s"><v>3195</v></c><c r="N13"><v>0</v></c></row><row r="14" spans="1:14"><c r="A14" t="s"><v>109</v></c><c r="B14" t="s"><v>18</v></c><c r="C14" t="s"><v>3082</v></c><c r="D14" t="s"><v>3085</v></c><c r="E14" t="s"><v>21636</v></c><c r="F14" t="s"><v>83</v></c><c r="G14" t="s"><v>21639</v></c><c r="H14" t="s"><v>21637</v></c><c r="I14" t="s"><v>21638</v></c><c r="K14" t="s"><v>3143</v></c><c r="L14" t="s"><v>3144</v></c><c r="M14" t="s"><v>3195</v></c><c r="N14"><v>0</v></c></row><row r="15" spans="1:14"><c r="A15" t="s"><v>116</v></c><c r="B15" t="s"><v>18</v></c><c r="C15" t="s"><v>3333</v></c><c r="D15" t="s"><v>3335</v></c><c r="E15" t="s"><v>21640</v></c><c r="F15" t="s"><v>83</v></c><c r="G15" t="s"><v>21641</v></c><c r="H15" t="s"><v>21642</v></c><c r="I15" t="s"><v>21643</v></c><c r="K15" t="s"><v>21644</v></c><c r="L15" t="s"><v>202</v></c><c r="M15" t="s"><v>3578</v></c><c r="N15"><v>0</v></c></row><row r="16" spans="1:14"><c r="A16" t="s"><v>122</v></c><c r="B16" t="s"><v>18</v></c><c r="C16" t="s"><v>3909</v></c><c r="D16" t="s"><v>3912</v></c><c r="E16" t="s"><v>21645</v></c><c r="F16" t="s"><v>83</v></c><c r="G16" t="s"><v>21646</v></c><c r="H16" t="s"><v>21647</v></c><c r="I16" t="s"><v>21648</v></c><c r="K16" t="s"><v>21649</v></c><c r="L16" t="s"><v>193</v></c><c r="M16" t="s"><v>4292</v></c><c r="N16"><v>0</v></c></row><row r="17" spans="1:14"><c r="A17" t="s"><v>128</v></c><c r="B17" t="s"><v>18</v></c><c r="C17" t="s"><v>4073</v></c><c r="D17" t="s"><v>4345</v></c><c r="E17" t="s"><v>21650</v></c><c r="F17" t="s"><v>2330</v></c><c r="G17" t="s"><v>3460</v></c><c r="H17" t="s"><v>21651</v></c><c r="I17" t="s"><v>21652</v></c><c r="K17" t="s"><v>4073</v></c><c r="L17" t="s"><v>48</v></c><c r="M17" t="s"><v>21653</v></c><c r="N17"><v>0</v></c></row><row r="18" spans="1:14"><c r="A18" t="s"><v>134</v></c><c r="B18" t="s"><v>18</v></c><c r="C18" t="s"><v>4878</v></c><c r="D18" t="s"><v>4881</v></c><c r="E18" t="s"><v>21654</v></c><c r="F18" t="s"><v>4076</v></c><c r="G18" t="s"><v>21655</v></c><c r="H18" t="s"><v>21656</v></c><c r="I18" t="s"><v>21657</v></c><c r="L18" t="s"><v>921</v></c><c r="M18" t="s"><v>4896</v></c><c r="N18"><v>0</v></c></row><row r="19" spans="1:14"><c r="A19" t="s"><v>139</v></c><c r="B19" t="s"><v>18</v></c><c r="C19" t="s"><v>4878</v></c><c r="D19" t="s"><v>4881</v></c><c r="E19" t="s"><v>21654</v></c><c r="F19" t="s"><v>4076</v></c><c r="G19" t="s"><v>4076</v></c><c r="H19" t="s"><v>21656</v></c><c r="I19" t="s"><v>21657</v></c><c r="L19" t="s"><v>921</v></c><c r="M19" t="s"><v>4896</v></c><c r="N19"><v>0</v></c></row><row r="20" spans="1:14"><c r="A20" t="s"><v>144</v></c><c r="B20" t="s"><v>18</v></c><c r="C20" t="s"><v>4878</v></c><c r="D20" t="s"><v>4881</v></c><c r="E20" t="s"><v>21654</v></c><c r="F20" t="s"><v>4076</v></c><c r="G20" t="s"><v>21658</v></c><c r="H20" t="s"><v>21656</v></c><c r="I20" t="s"><v>21657</v></c><c r="L20" t="s"><v>921</v></c><c r="M20" t="s"><v>4896</v></c><c r="N20"><v>0</v></c></row><row r="21" spans="1:14"><c r="A21" t="s"><v>153</v></c><c r="B21" t="s"><v>18</v></c><c r="C21" t="s"><v>4878</v></c><c r="D21" t="s"><v>4881</v></c><c r="E21" t="s"><v>21654</v></c><c r="F21" t="s"><v>4076</v></c><c r="G21" t="s"><v>4076</v></c><c r="H21" t="s"><v>21656</v></c><c r="I21" t="s"><v>21657</v></c><c r="L21" t="s"><v>921</v></c><c r="M21" t="s"><v>4896</v></c><c r="N21"><v>0</v></c></row><row r="22" spans="1:14"><c r="A22" t="s"><v>161</v></c><c r="B22" t="s"><v>18</v></c><c r="C22" t="s"><v>1906</v></c><c r="D22" t="s"><v>1909</v></c><c r="E22" t="s"><v>21609</v></c><c r="F22" t="s"><v>83</v></c><c r="G22" t="s"><v>1911</v></c><c r="H22" t="s"><v>21659</v></c><c r="I22" t="s"><v>21660</v></c><c r="K22" t="s"><v>21661</v></c><c r="L22" t="s"><v>193</v></c><c r="M22" t="s"><v>4907</v></c><c r="N22"><v>0</v></c></row><row r="23" spans="1:14"><c r="A23" t="s"><v>162</v></c><c r="B23" t="s"><v>18</v></c><c r="C23" t="s"><v>3397</v></c><c r="D23" t="s"><v>3398</v></c><c r="E23" t="s"><v>21662</v></c><c r="F23" t="s"><v>101</v></c><c r="G23" t="s"><v>101</v></c><c r="H23" t="s"><v>21663</v></c><c r="I23" t="s"><v>21664</v></c><c r="K23" t="s"><v>21665</v></c><c r="L23" t="s"><v>202</v></c><c r="M23" t="s"><v>5086</v></c><c r="N23"><v>1</v></c></row><row r="24" spans="1:14"><c r="A24" t="s"><v>170</v></c><c r="B24" t="s"><v>18</v></c><c r="C24" t="s"><v>5105</v></c><c r="D24" t="s"><v>5107</v></c><c r="E24" t="s"><v>21666</v></c><c r="F24" t="s"><v>2180</v></c><c r="G24" t="s"><v>21667</v></c><c r="H24" t="s"><v>21668</v></c><c r="I24" t="s"><v>21669</v></c><c r="K24" t="s"><v>21670</v></c><c r="L24" t="s"><v>7806</v></c><c r="M24" t="s"><v>5143</v></c><c r="N24"><v>0</v></c></row><row r="25" spans="1:14"><c r="A25" t="s"><v>176</v></c><c r="B25" t="s"><v>18</v></c><c r="C25" t="s"><v>5021</v></c><c r="D25" t="s"><v>5155</v></c><c r="E25" t="s"><v>21671</v></c><c r="F25" t="s"><v>2180</v></c><c r="G25" t="s"><v>2180</v></c><c r="H25" t="s"><v>21672</v></c><c r="I25" t="s"><v>21673</v></c><c r="K25" t="s"><v>21674</v></c><c r="L25" t="s"><v>186</v></c><c r="M25" t="s"><v>21675</v></c><c r="N25"><v>0</v></c></row><row r="26" spans="1:14"><c r="A26" t="s"><v>185</v></c><c r="B26" t="s"><v>18</v></c><c r="C26" t="s"><v>5021</v></c><c r="D26" t="s"><v>5155</v></c><c r="E26" t="s"><v>21676</v></c><c r="F26" t="s"><v>4869</v></c><c r="G26" t="s"><v>4869</v></c><c r="H26" t="s"><v>21677</v></c><c r="I26" t="s"><v>21678</v></c><c r="K26" t="s"><v>21679</v></c><c r="L26" t="s"><v>186</v></c><c r="M26" t="s"><v>21675</v></c><c r="N26"><v>0</v></c></row><row r="27" spans="1:14"><c r="A27" t="s"><v>194</v></c><c r="B27" t="s"><v>18</v></c><c r="C27" t="s"><v>6368</v></c><c r="D27" t="s"><v>6370</v></c><c r="E27" t="s"><v>21680</v></c><c r="F27" t="s"><v>1182</v></c><c r="G27" t="s"><v>1182</v></c><c r="H27" t="s"><v>21681</v></c><c r="I27" t="s"><v>21682</v></c><c r="K27" t="s"><v>21683</v></c><c r="L27" t="s"><v>3144</v></c><c r="M27" t="s"><v>6670</v></c><c r="N27"><v>0</v></c></row><row r="28" spans="1:14"><c r="A28" t="s"><v>203</v></c><c r="B28" t="s"><v>18</v></c><c r="C28" t="s"><v>6368</v></c><c r="D28" t="s"><v>6370</v></c><c r="E28" t="s"><v>21684</v></c><c r="F28" t="s"><v>3743</v></c><c r="G28" t="s"><v>21685</v></c><c r="H28" t="s"><v>21681</v></c><c r="I28" t="s"><v>21682</v></c><c r="K28" t="s"><v>21686</v></c><c r="L28" t="s"><v>3144</v></c><c r="M28" t="s"><v>6670</v></c><c r="N28"><v>0</v></c></row><row r="29" spans="1:14"><c r="A29" t="s"><v>210</v></c><c r="B29" t="s"><v>18</v></c><c r="C29" t="s"><v>6368</v></c><c r="D29" t="s"><v>6370</v></c><c r="E29" t="s"><v>21687</v></c><c r="F29" t="s"><v>1182</v></c><c r="G29" t="s"><v>1182</v></c><c r="H29" t="s"><v>21681</v></c><c r="I29" t="s"><v>21682</v></c><c r="K29" t="s"><v>21688</v></c><c r="L29" t="s"><v>3144</v></c><c r="M29" t="s"><v>6670</v></c><c r="N29"><v>0</v></c></row><row r="30" spans="1:14"><c r="A30" t="s"><v>217</v></c><c r="B30" t="s"><v>18</v></c><c r="C30" t="s"><v>6349</v></c><c r="D30" t="s"><v>6351</v></c><c r="E30" t="s"><v>21650</v></c><c r="F30" t="s"><v>2180</v></c><c r="G30" t="s"><v>21689</v></c><c r="H30" t="s"><v>21690</v></c><c r="I30" t="s"><v>21691</v></c><c r="K30" t="s"><v>1449</v></c><c r="L30" t="s"><v>195</v></c><c r="M30" t="s"><v>6706</v></c><c r="N30"><v>0</v></c></row><row r="31" spans="1:14"><c r="A31" t="s"><v>225</v></c><c r="B31" t="s"><v>18</v></c><c r="C31" t="s"><v>6349</v></c><c r="D31" t="s"><v>6351</v></c><c r="E31" t="s"><v>21650</v></c><c r="F31" t="s"><v>14662</v></c><c r="G31" t="s"><v>14662</v></c><c r="H31" t="s"><v>21690</v></c><c r="I31" t="s"><v>21691</v></c><c r="K31" t="s"><v>1449</v></c><c r="L31" t="s"><v>195</v></c><c r="M31" t="s"><v>6706</v></c><c r="N31"><v>0</v></c></row><row r="32" spans="1:14"><c r="A32" t="s"><v>231</v></c><c r="B32" t="s"><v>18</v></c><c r="C32" t="s"><v>6326</v></c><c r="D32" t="s"><v>6328</v></c><c r="E32" t="s"><v>21692</v></c><c r="F32" t="s"><v>2180</v></c><c r="G32" t="s"><v>2180</v></c><c r="H32" t="s"><v>21693</v></c><c r="I32" t="s"><v>21694</v></c><c r="K32" t="s"><v>21695</v></c><c r="L32" t="s"><v>1191</v></c><c r="M32" t="s"><v>6706</v></c><c r="N32"><v>0</v></c></row><row r="33" spans="1:14"><c r="A33" t="s"><v>238</v></c><c r="B33" t="s"><v>18</v></c><c r="C33" t="s"><v>6326</v></c><c r="D33" t="s"><v>6328</v></c><c r="E33" t="s"><v>21696</v></c><c r="F33" t="s"><v>45</v></c><c r="G33" t="s"><v>45</v></c><c r="H33" t="s"><v>21693</v></c><c r="I33" t="s"><v>21694</v></c><c r="K33" t="s"><v>21697</v></c><c r="L33" t="s"><v>1191</v></c><c r="M33" t="s"><v>6706</v></c><c r="N33"><v>0</v></c></row><row r="34" spans="1:14"><c r="A34" t="s"><v>248</v></c><c r="B34" t="s"><v>18</v></c><c r="C34" t="s"><v>6359</v></c><c r="D34" t="s"><v>6360</v></c><c r="E34" t="s"><v>21698</v></c><c r="F34" t="s"><v>2180</v></c><c r="G34" t="s"><v>2180</v></c><c r="H34" t="s"><v>21699</v></c><c r="I34" t="s"><v>21700</v></c><c r="K34" t="s"><v>21701</v></c><c r="L34" t="s"><v>1191</v></c><c r="M34" t="s"><v>6706</v></c><c r="N34"><v>0</v></c></row><row r="35" spans="1:14"><c r="A35" t="s"><v>257</v></c><c r="B35" t="s"><v>18</v></c><c r="C35" t="s"><v>6359</v></c><c r="D35" t="s"><v>6360</v></c><c r="E35" t="s"><v>21702</v></c><c r="F35" t="s"><v>45</v></c><c r="G35" t="s"><v>45</v></c><c r="H35" t="s"><v>21699</v></c><c r="I35" t="s"><v>21700</v></c><c r="K35" t="s"><v>21703</v></c><c r="L35" t="s"><v>1191</v></c><c r="M35" t="s"><v>6706</v></c><c r="N35"><v>0</v></c></row><row r="36" spans="1:14"><c r="A36" t="s"><v>265</v></c><c r="B36" t="s"><v>18</v></c><c r="C36" t="s"><v>6320</v></c><c r="D36" t="s"><v>6322</v></c><c r="E36" t="s"><v>21698</v></c><c r="F36" t="s"><v>2180</v></c><c r="G36" t="s"><v>2180</v></c><c r="H36" t="s"><v>21704</v></c><c r="I36" t="s"><v>21705</v></c><c r="K36" t="s"><v>21706</v></c><c r="L36" t="s"><v>1191</v></c><c r="M36" t="s"><v>6706</v></c><c r="N36"><v>0</v></c></row><row r="37" spans="1:14"><c r="A37" t="s"><v>274</v></c><c r="B37" t="s"><v>18</v></c><c r="C37" t="s"><v>6320</v></c><c r="D37" t="s"><v>6322</v></c><c r="E37" t="s"><v>21702</v></c><c r="F37" t="s"><v>1217</v></c><c r="G37" t="s"><v>1217</v></c><c r="H37" t="s"><v>21707</v></c><c r="I37" t="s"><v>21708</v></c><c r="K37" t="s"><v>21709</v></c><c r="L37" t="s"><v>1191</v></c><c r="M37" t="s"><v>6706</v></c><c r="N37"><v>0</v></c></row><row r="38" spans="1:14"><c r="A38" t="s"><v>283</v></c><c r="B38" t="s"><v>18</v></c><c r="C38" t="s"><v>6320</v></c><c r="D38" t="s"><v>6322</v></c><c r="E38" t="s"><v>21710</v></c><c r="F38" t="s"><v>1217</v></c><c r="G38" t="s"><v>4257</v></c><c r="H38" t="s"><v>21711</v></c><c r="I38" t="s"><v>21712</v></c><c r="K38" t="s"><v>21713</v></c><c r="L38" t="s"><v>1191</v></c><c r="M38" t="s"><v>6706</v></c><c r="N38"><v>0</v></c></row><row r="39" spans="1:14"><c r="A39" t="s"><v>291</v></c><c r="B39" t="s"><v>18</v></c><c r="C39" t="s"><v>6368</v></c><c r="D39" t="s"><v>6370</v></c><c r="E39" t="s"><v>21714</v></c><c r="F39" t="s"><v>3743</v></c><c r="G39" t="s"><v>3743</v></c><c r="H39" t="s"><v>21681</v></c><c r="I39" t="s"><v>21682</v></c><c r="K39" t="s"><v>3143</v></c><c r="L39" t="s"><v>3144</v></c><c r="M39" t="s"><v>6706</v></c><c r="N39"><v>0</v></c></row><row r="40" spans="1:14"><c r="A40" t="s"><v>297</v></c><c r="B40" t="s"><v>18</v></c><c r="C40" t="s"><v>6368</v></c><c r="D40" t="s"><v>6370</v></c><c r="E40" t="s"><v>21714</v></c><c r="F40" t="s"><v>1182</v></c><c r="G40" t="s"><v>1182</v></c><c r="H40" t="s"><v>21681</v></c><c r="I40" t="s"><v>21682</v></c><c r="K40" t="s"><v>3143</v></c><c r="L40" t="s"><v>3144</v></c><c r="M40" t="s"><v>6706</v></c><c r="N40"><v>0</v></c></row><row r="41" spans="1:14"><c r="A41" t="s"><v>303</v></c><c r="B41" t="s"><v>18</v></c><c r="C41" t="s"><v>6301</v></c><c r="D41" t="s"><v>6303</v></c><c r="E41" t="s"><v>21715</v></c><c r="F41" t="s"><v>83</v></c><c r="G41" t="s"><v>83</v></c><c r="H41" t="s"><v>21716</v></c><c r="I41" t="s"><v>21717</v></c><c r="K41" t="s"><v>21718</v></c><c r="L41" t="s"><v>103</v></c><c r="M41" t="s"><v>6706</v></c><c r="N41"><v>0</v></c></row><row r="42" spans="1:14"><c r="A42" t="s"><v>310</v></c><c r="B42" t="s"><v>18</v></c><c r="C42" t="s"><v>6301</v></c><c r="D42" t="s"><v>6303</v></c><c r="E42" t="s"><v>21719</v></c><c r="F42" t="s"><v>21720</v></c><c r="G42" t="s"><v>21720</v></c><c r="H42" t="s"><v>21716</v></c><c r="I42" t="s"><v>21717</v></c><c r="K42" t="s"><v>21721</v></c><c r="L42" t="s"><v>103</v></c><c r="M42" t="s"><v>6706</v></c><c r="N42"><v>0</v></c></row><row r="43" spans="1:14"><c r="A43" t="s"><v>315</v></c><c r="B43" t="s"><v>18</v></c><c r="C43" t="s"><v>6636</v></c><c r="D43" t="s"><v>6637</v></c><c r="E43" t="s"><v>21722</v></c><c r="F43" t="s"><v>21720</v></c><c r="G43" t="s"><v>21723</v></c><c r="H43" t="s"><v>21724</v></c><c r="I43" t="s"><v>21725</v></c><c r="K43" t="s"><v>21726</v></c><c r="L43" t="s"><v>284</v></c><c r="M43" t="s"><v>6706</v></c><c r="N43"><v>0</v></c></row><row r="44" spans="1:14"><c r="A44" t="s"><v>322</v></c><c r="B44" t="s"><v>18</v></c><c r="C44" t="s"><v>5246</v></c><c r="D44" t="s"><v>5248</v></c><c r="E44" t="s"><v>21727</v></c><c r="F44" t="s"><v>83</v></c><c r="G44" t="s"><v>83</v></c><c r="H44" t="s"><v>21728</v></c><c r="I44" t="s"><v>21729</v></c><c r="K44" t="s"><v>4585</v></c><c r="L44" t="s"><v>177</v></c><c r="M44" t="s"><v>6895</v></c><c r="N44"><v>0</v></c></row><row r="45" spans="1:14"><c r="A45" t="s"><v>329</v></c><c r="B45" t="s"><v>18</v></c><c r="C45" t="s"><v>5246</v></c><c r="D45" t="s"><v>5248</v></c><c r="E45" t="s"><v>21730</v></c><c r="F45" t="s"><v>83</v></c><c r="G45" t="s"><v>21731</v></c><c r="H45" t="s"><v>21728</v></c><c r="I45" t="s"><v>21729</v></c><c r="K45" t="s"><v>4585</v></c><c r="L45" t="s"><v>177</v></c><c r="M45" t="s"><v>6895</v></c><c r="N45"><v>0</v></c></row><row r="46" spans="1:14"><c r="A46" t="s"><v>336</v></c><c r="B46" t="s"><v>18</v></c><c r="C46" t="s"><v>5332</v></c><c r="D46" t="s"><v>5334</v></c><c r="E46" t="s"><v>21732</v></c><c r="F46" t="s"><v>158</v></c><c r="G46" t="s"><v>158</v></c><c r="H46" t="s"><v>21733</v></c><c r="I46" t="s"><v>21734</v></c><c r="K46" t="s"><v>21735</v></c><c r="L46" t="s"><v>3144</v></c><c r="M46" t="s"><v>7000</v></c><c r="N46"><v>0</v></c></row><row r="47" spans="1:14"><c r="A47" t="s"><v>344</v></c><c r="B47" t="s"><v>18</v></c><c r="C47" t="s"><v>6825</v></c><c r="D47" t="s"><v>6836</v></c><c r="E47" t="s"><v>21650</v></c><c r="F47" t="s"><v>21736</v></c><c r="G47" t="s"><v>1157</v></c><c r="H47" t="s"><v>21737</v></c><c r="I47" t="s"><v>21738</v></c><c r="K47" t="s"><v>1449</v></c><c r="L47" t="s"><v>195</v></c><c r="M47" t="s"><v>7044</v></c><c r="N47"><v>0</v></c></row><row r="48" spans="1:14"><c r="A48" t="s"><v>351</v></c><c r="B48" t="s"><v>18</v></c><c r="C48" t="s"><v>6825</v></c><c r="D48" t="s"><v>6840</v></c><c r="E48" t="s"><v>21650</v></c><c r="F48" t="s"><v>21736</v></c><c r="G48" t="s"><v>158</v></c><c r="H48" t="s"><v>21739</v></c><c r="I48" t="s"><v>21740</v></c><c r="K48" t="s"><v>1449</v></c><c r="L48" t="s"><v>195</v></c><c r="M48" t="s"><v>7044</v></c><c r="N48"><v>0</v></c></row><row r="49" spans="1:14"><c r="A49" t="s"><v>358</v></c><c r="B49" t="s"><v>18</v></c><c r="C49" t="s"><v>6825</v></c><c r="D49" t="s"><v>6852</v></c><c r="E49" t="s"><v>21650</v></c><c r="F49" t="s"><v>21736</v></c><c r="G49" t="s"><v>158</v></c><c r="H49" t="s"><v>21739</v></c><c r="I49" t="s"><v>21740</v></c><c r="K49" t="s"><v>1449</v></c><c r="L49" t="s"><v>195</v></c><c r="M49" t="s"><v>7044</v></c><c r="N49"><v>0</v></c></row><row r="50" spans="1:14"><c r="A50" t="s"><v>363</v></c><c r="B50" t="s"><v>18</v></c><c r="C50" t="s"><v>6825</v></c><c r="D50" t="s"><v>6832</v></c><c r="E50" t="s"><v>21650</v></c><c r="F50" t="s"><v>21736</v></c><c r="G50" t="s"><v>158</v></c><c r="H50" t="s"><v>21739</v></c><c r="I50" t="s"><v>21740</v></c><c r="K50" t="s"><v>1449</v></c><c r="L50" t="s"><v>195</v></c><c r="M50" t="s"><v>7044</v></c><c r="N50"><v>0</v></c></row><row r="51" spans="1:14"><c r="A51" t="s"><v>368</v></c><c r="B51" t="s"><v>18</v></c><c r="C51" t="s"><v>6825</v></c><c r="D51" t="s"><v>6844</v></c><c r="E51" t="s"><v>21650</v></c><c r="F51" t="s"><v>21736</v></c><c r="G51" t="s"><v>158</v></c><c r="H51" t="s"><v>21739</v></c><c r="I51" t="s"><v>21740</v></c><c r="K51" t="s"><v>1449</v></c><c r="L51" t="s"><v>195</v></c><c r="M51" t="s"><v>7044</v></c><c r="N51"><v>0</v></c></row><row r="52" spans="1:14"><c r="A52" t="s"><v>374</v></c><c r="B52" t="s"><v>18</v></c><c r="C52" t="s"><v>6825</v></c><c r="D52" t="s"><v>6828</v></c><c r="E52" t="s"><v>21650</v></c><c r="F52" t="s"><v>21736</v></c><c r="G52" t="s"><v>158</v></c><c r="H52" t="s"><v>21739</v></c><c r="I52" t="s"><v>21740</v></c><c r="K52" t="s"><v>1449</v></c><c r="L52" t="s"><v>195</v></c><c r="M52" t="s"><v>7044</v></c><c r="N52"><v>0</v></c></row><row r="53" spans="1:14"><c r="A53" t="s"><v>379</v></c><c r="B53" t="s"><v>18</v></c><c r="C53" t="s"><v>6779</v></c><c r="D53" t="s"><v>6782</v></c><c r="E53" t="s"><v>21741</v></c><c r="F53" t="s"><v>149</v></c><c r="G53" t="s"><v>21742</v></c><c r="H53" t="s"><v>21743</v></c><c r="I53" t="s"><v>21744</v></c><c r="K53" t="s"><v>4585</v></c><c r="L53" t="s"><v>177</v></c><c r="M53" t="s"><v>7044</v></c><c r="N53"><v>0</v></c></row><row r="54" spans="1:14"><c r="A54" t="s"><v>385</v></c><c r="B54" t="s"><v>18</v></c><c r="C54" t="s"><v>6779</v></c><c r="D54" t="s"><v>6782</v></c><c r="E54" t="s"><v>21745</v></c><c r="F54" t="s"><v>101</v></c><c r="G54" t="s"><v>101</v></c><c r="H54" t="s"><v>21746</v></c><c r="I54" t="s"><v>21747</v></c><c r="K54" t="s"><v>4585</v></c><c r="L54" t="s"><v>177</v></c><c r="M54" t="s"><v>7044</v></c><c r="N54"><v>0</v></c></row><row r="55" spans="1:14"><c r="A55" t="s"><v>392</v></c><c r="B55" t="s"><v>18</v></c><c r="C55" t="s"><v>5344</v></c><c r="D55" t="s"><v>5346</v></c><c r="E55" t="s"><v>21748</v></c><c r="F55" t="s"><v>45</v></c><c r="G55" t="s"><v>45</v></c><c r="H55" t="s"><v>21749</v></c><c r="I55" t="s"><v>21750</v></c><c r="K55" t="s"><v>21622</v></c><c r="L55" t="s"><v>163</v></c><c r="M55" t="s"><v>7081</v></c><c r="N55"><v>0</v></c></row><row r="56" spans="1:14"><c r="A56" t="s"><v>397</v></c><c r="B56" t="s"><v>18</v></c><c r="C56" t="s"><v>985</v></c><c r="D56" t="s"><v>987</v></c><c r="E56" t="s"><v>21751</v></c><c r="F56" t="s"><v>21752</v></c><c r="G56" t="s"><v>988</v></c><c r="H56" t="s"><v>21753</v></c><c r="I56" t="s"><v>21754</v></c><c r="K56" t="s"><v>21755</v></c><c r="L56" t="s"><v>183</v></c><c r="M56" t="s"><v>21756</v></c><c r="N56"><v>0</v></c></row><row r="57" spans="1:14"><c r="A57" t="s"><v>402</v></c><c r="B57" t="s"><v>18</v></c><c r="C57" t="s"><v>7102</v></c><c r="D57" t="s"><v>7105</v></c><c r="E57" t="s"><v>21757</v></c><c r="F57" t="s"><v>67</v></c><c r="G57" t="s"><v>67</v></c><c r="H57" t="s"><v>21758</v></c><c r="I57" t="s"><v>21759</v></c><c r="K57" t="s"><v>21760</v></c><c r="L57" t="s"><v>7101</v></c><c r="M57" t="s"><v>21761</v></c><c r="N57"><v>0</v></c></row><row r="58" spans="1:14"><c r="A58" t="s"><v>407</v></c><c r="B58" t="s"><v>18</v></c><c r="C58" t="s"><v>7614</v></c><c r="D58" t="s"><v>7617</v></c><c r="E58" t="s"><v>21762</v></c><c r="F58" t="s"><v>2180</v></c><c r="G58" t="s"><v>21763</v></c><c r="H58" t="s"><v>21764</v></c><c r="I58" t="s"><v>21765</v></c><c r="K58" t="s"><v>21766</v></c><c r="L58" t="s"><v>48</v></c><c r="M58" t="s"><v>7631</v></c><c r="N58"><v>0</v></c></row><row r="59" spans="1:14"><c r="A59" t="s"><v>412</v></c><c r="B59" t="s"><v>18</v></c><c r="C59" t="s"><v>6677</v></c><c r="D59" t="s"><v>6679</v></c><c r="E59" t="s"><v>21767</v></c><c r="F59" t="s"><v>1555</v></c><c r="G59" t="s"><v>549</v></c><c r="H59" t="s"><v>21768</v></c><c r="I59" t="s"><v>21769</v></c><c r="K59" t="s"><v>21770</v></c><c r="L59" t="s"><v>202</v></c><c r="M59" t="s"><v>20983</v></c><c r="N59"><v>0</v></c></row><row r="60" spans="1:14"><c r="A60" t="s"><v>417</v></c><c r="B60" t="s"><v>18</v></c><c r="C60" t="s"><v>6344</v></c><c r="D60" t="s"><v>6345</v></c><c r="E60" t="s"><v>21714</v></c><c r="F60" t="s"><v>2180</v></c><c r="G60" t="s"><v>11285</v></c><c r="H60" t="s"><v>21771</v></c><c r="I60" t="s"><v>21772</v></c><c r="K60" t="s"><v>21773</v></c><c r="L60" t="s"><v>202</v></c><c r="M60" t="s"><v>21774</v></c><c r="N60"><v>0</v></c></row><row r="61" spans="1:14"><c r="A61" t="s"><v>422</v></c><c r="B61" t="s"><v>18</v></c><c r="C61" t="s"><v>6344</v></c><c r="D61" t="s"><v>6345</v></c><c r="E61" t="s"><v>21775</v></c><c r="F61" t="s"><v>2180</v></c><c r="G61" t="s"><v>21776</v></c><c r="H61" t="s"><v>21777</v></c><c r="I61" t="s"><v>21778</v></c><c r="K61" t="s"><v>21779</v></c><c r="L61" t="s"><v>202</v></c><c r="M61" t="s"><v>21774</v></c><c r="N61"><v>0</v></c></row><row r="62" spans="1:14"><c r="A62" t="s"><v>429</v></c><c r="B62" t="s"><v>18</v></c><c r="C62" t="s"><v>6332</v></c><c r="D62" t="s"><v>6334</v></c><c r="E62" t="s"><v>21780</v></c><c r="F62" t="s"><v>2857</v></c><c r="G62" t="s"><v>4643</v></c><c r="H62" t="s"><v>21781</v></c><c r="I62" t="s"><v>21778</v></c><c r="K62" t="s"><v>21782</v></c><c r="L62" t="s"><v>202</v></c><c r="M62" t="s"><v>21783</v></c><c r="N62"><v>0</v></c></row><row r="63" spans="1:14"><c r="A63" t="s"><v>434</v></c><c r="B63" t="s"><v>18</v></c><c r="C63" t="s"><v>6332</v></c><c r="D63" t="s"><v>6334</v></c><c r="E63" t="s"><v>21784</v></c><c r="F63" t="s"><v>3834</v></c><c r="G63" t="s"><v>2180</v></c><c r="H63" t="s"><v>21771</v></c><c r="I63" t="s"><v>21772</v></c><c r="K63" t="s"><v>21785</v></c><c r="L63" t="s"><v>202</v></c><c r="M63" t="s"><v>21783</v></c><c r="N63"><v>0</v></c></row><row r="64" spans="1:14"><c r="A64" t="s"><v>439</v></c><c r="B64" t="s"><v>18</v></c><c r="C64" t="s"><v>8303</v></c><c r="D64" t="s"><v>8306</v></c><c r="E64" t="s"><v>21786</v></c><c r="F64" t="s"><v>158</v></c><c r="G64" t="s"><v>21787</v></c><c r="H64" t="s"><v>21788</v></c><c r="I64" t="s"><v>21789</v></c><c r="K64" t="s"><v>4585</v></c><c r="L64" t="s"><v>177</v></c><c r="M64" t="s"><v>8484</v></c><c r="N64"><v>0</v></c></row><row r="65" spans="1:14"><c r="A65" t="s"><v>444</v></c><c r="B65" t="s"><v>18</v></c><c r="C65" t="s"><v>8297</v></c><c r="D65" t="s"><v>8300</v></c><c r="E65" t="s"><v>21790</v></c><c r="F65" t="s"><v>2267</v></c><c r="G65" t="s"><v>21791</v></c><c r="H65" t="s"><v>21792</v></c><c r="I65" t="s"><v>21793</v></c><c r="K65" t="s"><v>4585</v></c><c r="L65" t="s"><v>177</v></c><c r="M65" t="s"><v>8484</v></c><c r="N65"><v>0</v></c></row><row r="66" spans="1:14"><c r="A66" t="s"><v>449</v></c><c r="B66" t="s"><v>18</v></c><c r="C66" t="s"><v>5084</v></c><c r="D66" t="s"><v>5085</v></c><c r="E66" t="s"><v>21794</v></c><c r="F66" t="s"><v>89</v></c><c r="G66" t="s"><v>21795</v></c><c r="H66" t="s"><v>21796</v></c><c r="I66" t="s"><v>21797</v></c><c r="K66" t="s"><v>21798</v></c><c r="L66" t="s"><v>799</v></c><c r="M66" t="s"><v>21799</v></c><c r="N66"><v>0</v></c></row><row r="67" spans="1:14"><c r="A67" t="s"><v>455</v></c><c r="B67" t="s"><v>18</v></c><c r="C67" t="s"><v>9906</v></c><c r="D67" t="s"><v>9909</v></c><c r="E67" t="s"><v>21800</v></c><c r="F67" t="s"><v>83</v></c><c r="G67" t="s"><v>21801</v></c><c r="H67" t="s"><v>21802</v></c><c r="I67" t="s"><v>21803</v></c><c r="K67" t="s"><v>21804</v></c><c r="L67" t="s"><v>3144</v></c><c r="M67" t="s"><v>10279</v></c><c r="N67"><v>0</v></c></row><row r="68" spans="1:14"><c r="A68" t="s"><v>461</v></c><c r="B68" t="s"><v>18</v></c><c r="C68" t="s"><v>10409</v></c><c r="D68" t="s"><v>10411</v></c><c r="E68" t="s"><v>21805</v></c><c r="F68" t="s"><v>1555</v></c><c r="G68" t="s"><v>36</v></c><c r="H68" t="s"><v>21806</v></c><c r="I68" t="s"><v>21807</v></c><c r="K68" t="s"><v>21808</v></c><c r="L68" t="s"><v>123</v></c><c r="M68" t="s"><v>11055</v></c><c r="N68"><v>0</v></c></row><row r="69" spans="1:14"><c r="A69" t="s"><v>467</v></c><c r="B69" t="s"><v>18</v></c><c r="C69" t="s"><v>11958</v></c><c r="D69" t="s"><v>11960</v></c><c r="E69" t="s"><v>21809</v></c><c r="F69" t="s"><v>2180</v></c><c r="G69" t="s"><v>10552</v></c><c r="H69" t="s"><v>21810</v></c><c r="I69" t="s"><v>21811</v></c><c r="K69" t="s"><v>21812</v></c><c r="L69" t="s"><v>123</v></c><c r="M69" t="s"><v>21813</v></c><c r="N69"><v>0</v></c></row><row r="70" spans="1:14"><c r="A70" t="s"><v>473</v></c><c r="B70" t="s"><v>18</v></c><c r="C70" t="s"><v>11958</v></c><c r="D70" t="s"><v>11960</v></c><c r="E70" t="s"><v>21809</v></c><c r="F70" t="s"><v>2180</v></c><c r="G70" t="s"><v>11438</v></c><c r="H70" t="s"><v>21810</v></c><c r="I70" t="s"><v>21811</v></c><c r="K70" t="s"><v>21814</v></c><c r="L70" t="s"><v>123</v></c><c r="M70" t="s"><v>21813</v></c><c r="N70"><v>0</v></c></row><row r="71" spans="1:14"><c r="A71" t="s"><v>478</v></c><c r="B71" t="s"><v>18</v></c><c r="C71" t="s"><v>12586</v></c><c r="D71" t="s"><v>12589</v></c><c r="E71" t="s"><v>21815</v></c><c r="F71" t="s"><v>89</v></c><c r="G71" t="s"><v>21816</v></c><c r="H71" t="s"><v>21817</v></c><c r="I71" t="s"><v>21818</v></c><c r="K71" t="s"><v>4585</v></c><c r="L71" t="s"><v>177</v></c><c r="M71" t="s"><v>13496</v></c><c r="N71"><v>0</v></c></row><row r="72" spans="1:14"><c r="A72" t="s"><v>483</v></c><c r="B72" t="s"><v>18</v></c><c r="C72" t="s"><v>13266</v></c><c r="D72" t="s"><v>13269</v></c><c r="E72" t="s"><v>21819</v></c><c r="F72" t="s"><v>1157</v></c><c r="G72" t="s"><v>21820</v></c><c r="H72" t="s"><v>21821</v></c><c r="I72" t="s"><v>21822</v></c><c r="K72" t="s"><v>21823</v></c><c r="L72" t="s"><v>28</v></c><c r="M72" t="s"><v>13496</v></c><c r="N72"><v>0</v></c></row><row r="73" spans="1:14"><c r="A73" t="s"><v>487</v></c><c r="B73" t="s"><v>18</v></c><c r="C73" t="s"><v>13039</v></c><c r="D73" t="s"><v>13042</v></c><c r="E73" t="s"><v>21824</v></c><c r="F73" t="s"><v>89</v></c><c r="G73" t="s"><v>21825</v></c><c r="H73" t="s"><v>21826</v></c><c r="I73" t="s"><v>21827</v></c><c r="K73" t="s"><v>4585</v></c><c r="L73" t="s"><v>177</v></c><c r="M73" t="s"><v>13496</v></c><c r="N73"><v>0</v></c></row><row r="74" spans="1:14"><c r="A74" t="s"><v>492</v></c><c r="B74" t="s"><v>18</v></c><c r="C74" t="s"><v>5290</v></c><c r="D74" t="s"><v>5292</v></c><c r="E74" t="s"><v>21828</v></c><c r="F74" t="s"><v>2315</v></c><c r="G74" t="s"><v>21829</v></c><c r="H74" t="s"><v>21830</v></c><c r="I74" t="s"><v>21831</v></c><c r="K74" t="s"><v>21832</v></c><c r="L74" t="s"><v>4741</v></c><c r="M74" t="s"><v>13496</v></c><c r="N74"><v>0</v></c></row><row r="75" spans="1:14"><c r="A75" t="s"><v>498</v></c><c r="B75" t="s"><v>18</v></c><c r="C75" t="s"><v>13818</v></c><c r="D75" t="s"><v>13821</v></c><c r="E75" t="s"><v>21833</v></c><c r="F75" t="s"><v>101</v></c><c r="G75" t="s"><v>11539</v></c><c r="H75" t="s"><v>21834</v></c><c r="I75" t="s"><v>21835</v></c><c r="K75" t="s"><v>4585</v></c><c r="L75" t="s"><v>177</v></c><c r="M75" t="s"><v>13897</v></c><c r="N75"><v>0</v></c></row><row r="76" spans="1:14"><c r="A76" t="s"><v>503</v></c><c r="B76" t="s"><v>18</v></c><c r="C76" t="s"><v>11761</v></c><c r="D76" t="s"><v>11763</v></c><c r="E76" t="s"><v>21836</v></c><c r="F76" t="s"><v>237</v></c><c r="G76" t="s"><v>45</v></c><c r="H76" t="s"><v>21837</v></c><c r="I76" t="s"><v>21838</v></c><c r="K76" t="s"><v>21839</v></c><c r="L76" t="s"><v>9030</v></c><c r="M76" t="s"><v>21840</v></c><c r="N76"><v>0</v></c></row><row r="77" spans="1:14"><c r="A77" t="s"><v>509</v></c><c r="B77" t="s"><v>18</v></c><c r="C77" t="s"><v>10863</v></c><c r="D77" t="s"><v>10866</v></c><c r="E77" t="s"><v>21841</v></c><c r="F77" t="s"><v>940</v></c><c r="G77" t="s"><v>940</v></c><c r="H77" t="s"><v>21842</v></c><c r="I77" t="s"><v>21843</v></c><c r="K77" t="s"><v>21844</v></c><c r="L77" t="s"><v>202</v></c><c r="M77" t="s"><v>14077</v></c><c r="N77"><v>1</v></c></row><row r="78" spans="1:14"><c r="A78" t="s"><v>514</v></c><c r="B78" t="s"><v>18</v></c><c r="C78" t="s"><v>9001</v></c><c r="D78" t="s"><v>9003</v></c><c r="E78" t="s"><v>21845</v></c><c r="F78" t="s"><v>67</v></c><c r="G78" t="s"><v>9042</v></c><c r="H78" t="s"><v>21846</v></c><c r="I78" t="s"><v>21847</v></c><c r="K78" t="s"><v>21848</v></c><c r="L78" t="s"><v>28</v></c><c r="M78" t="s"><v>21849</v></c><c r="N78"><v>0</v></c></row><row r="79" spans="1:14"><c r="A79" t="s"><v>518</v></c><c r="B79" t="s"><v>18</v></c><c r="C79" t="s"><v>9001</v></c><c r="D79" t="s"><v>9003</v></c><c r="E79" t="s"><v>21850</v></c><c r="F79" t="s"><v>67</v></c><c r="G79" t="s"><v>67</v></c><c r="H79" t="s"><v>21846</v></c><c r="I79" t="s"><v>21847</v></c><c r="K79" t="s"><v>21848</v></c><c r="L79" t="s"><v>28</v></c><c r="M79" t="s"><v>21849</v></c><c r="N79"><v>0</v></c></row><row r="80" spans="1:14"><c r="A80" t="s"><v>522</v></c><c r="B80" t="s"><v>18</v></c><c r="C80" t="s"><v>21349</v></c><c r="D80" t="s"><v>14405</v></c><c r="E80" t="s"><v>21851</v></c><c r="F80" t="s"><v>101</v></c><c r="G80" t="s"><v>21852</v></c><c r="H80" t="s"><v>21853</v></c><c r="I80" t="s"><v>21854</v></c><c r="K80" t="s"><v>4585</v></c><c r="L80" t="s"><v>177</v></c><c r="M80" t="s"><v>21351</v></c><c r="N80"><v>0</v></c></row><row r="81" spans="1:14"><c r="A81" t="s"><v>529</v></c><c r="B81" t="s"><v>18</v></c><c r="C81" t="s"><v>15155</v></c><c r="D81" t="s"><v>15158</v></c><c r="E81" t="s"><v>21855</v></c><c r="F81" t="s"><v>2351</v></c><c r="G81" t="s"><v>2351</v></c><c r="H81" t="s"><v>21856</v></c><c r="I81" t="s"><v>21857</v></c><c r="K81" t="s"><v>21858</v></c><c r="L81" t="s"><v>202</v></c><c r="M81" t="s"><v>15166</v></c><c r="N81"><v>0</v></c></row><row r="82" spans="1:14"><c r="A82" t="s"><v>536</v></c><c r="B82" t="s"><v>18</v></c><c r="C82" t="s"><v>15155</v></c><c r="D82" t="s"><v>15158</v></c><c r="E82" t="s"><v>21859</v></c><c r="F82" t="s"><v>2351</v></c><c r="G82" t="s"><v>2351</v></c><c r="H82" t="s"><v>21856</v></c><c r="I82" t="s"><v>21857</v></c><c r="K82" t="s"><v>21858</v></c><c r="L82" t="s"><v>202</v></c><c r="M82" t="s"><v>15179</v></c><c r="N82"><v>0</v></c></row><row r="83" spans="1:14"><c r="A83" t="s"><v>541</v></c><c r="B83" t="s"><v>18</v></c><c r="C83" t="s"><v>21414</v></c><c r="D83" t="s"><v>15224</v></c><c r="E83" t="s"><v>21860</v></c><c r="F83" t="s"><v>158</v></c><c r="G83" t="s"><v>21861</v></c><c r="H83" t="s"><v>21862</v></c><c r="I83" t="s"><v>21863</v></c><c r="K83" t="s"><v>4585</v></c><c r="L83" t="s"><v>177</v></c><c r="M83" t="s"><v>21864</v></c><c r="N83"><v>0</v></c></row><row r="84" spans="1:14"><c r="A84" t="s"><v>546</v></c><c r="B84" t="s"><v>18</v></c><c r="C84" t="s"><v>16198</v></c><c r="D84" t="s"><v>16199</v></c><c r="E84" t="s"><v>21865</v></c><c r="F84" t="s"><v>21866</v></c><c r="G84" t="s"><v>45</v></c><c r="H84" t="s"><v>21867</v></c><c r="I84" t="s"><v>21868</v></c><c r="K84" t="s"><v>21869</v></c><c r="L84" t="s"><v>92</v></c><c r="M84" t="s"><v>17830</v></c><c r="N84"><v>0</v></c></row><row r="85" spans="1:14"><c r="A85" t="s"><v>551</v></c><c r="B85" t="s"><v>18</v></c><c r="C85" t="s"><v>18754</v></c><c r="D85" t="s"><v>18757</v></c><c r="E85" t="s"><v>21870</v></c><c r="F85" t="s"><v>83</v></c><c r="G85" t="s"><v>21871</v></c><c r="H85" t="s"><v>21872</v></c><c r="I85" t="s"><v>21873</v></c><c r="K85" t="s"><v>21874</v></c><c r="L85" t="s"><v>1191</v></c><c r="M85" t="s"><v>18789</v></c><c r="N85"><v>0</v></c></row><row r="86" spans="1:14"><c r="A86" t="s"><v>556</v></c><c r="B86" t="s"><v>18</v></c><c r="C86" t="s"><v>15631</v></c><c r="D86" t="s"><v>15633</v></c><c r="E86" t="s"><v>21875</v></c><c r="F86" t="s"><v>1555</v></c><c r="G86" t="s"><v>15634</v></c><c r="H86" t="s"><v>21876</v></c><c r="I86" t="s"><v>21877</v></c><c r="K86" t="s"><v>21878</v></c><c r="L86" t="s"><v>3144</v></c><c r="M86" t="s"><v>19096</v></c><c r="N86"><v>0</v></c></row></sheetData><pageMargins left="0.75" right="0.75" top="0.75" bottom="0.5" header="0.5" footer="0.75"/><headerFooter/><tableParts count="1"><tablePart r:id="rId1"/></tableParts></worksheet>